{
  "bounds": {
    "localVertices": [
      800.0,
      400.0,
      800.0,
      4600.0,
      4200.0,
      4600.0,
      4200.0,
      400.0
    ],
    "x": 0.0,
    "y": 0.0,
    "originX": 0.0,
    "originY": 0.0,
    "rotation": 0.0,
    "scaleX": 1.0,
    "scaleY": 1.0,
    "dirty": true
  },
  "startPoint": {
    "x": 1000.0,
    "y": 1000.0
  },
  "backgroundPath": "bgTest.png",
  "entities": [
    {
      "collisionBox": {
        "localVertices": [
          0.0,
          0.0,
          0.0,
          40.0,
          50.0,
          20.0
        ],
        "x": 2500.0,
        "y": 400.0,
        "originX": 0.0,
        "originY": 0.0,
        "rotation": 0.0,
        "scaleX": 1.0,
        "scaleY": 1.0,
        "dirty": true
      },
      "pos": {
        "x": 2500.0,
        "y": 400.0
      },
      "spritePath": "playerTest.png",
      "hitPoints": 2
    },
    {
      "collisionBox": {
        "localVertices": [
          0.0,
          0.0,
          0.0,
          40.0,
          50.0,
          20.0
        ],
        "x": 2600.0,
        "y": 410.98816,
        "originX": 0.0,
        "originY": 0.0,
        "rotation": 0.0,
        "scaleX": 1.0,
        "scaleY": 1.0,
        "dirty": true
      },
      "pos": {
        "x": 2600.0,
        "y": 410.98816
      },
      "spritePath": "playerTest.png",
      "hitPoints": 2
    },
    {
      "collisionBox": {
        "localVertices": [
          0.0,
          0.0,
          0.0,
          40.0,
          50.0,
          20.0
        ],
        "x": 2700.0,
        "y": 571.4588,
        "originX": 0.0,
        "originY": 0.0,
        "rotation": 0.0,
        "scaleX": 1.0,
        "scaleY": 1.0,
        "dirty": true
      },
      "pos": {
        "x": 2700.0,
        "y": 571.4588
      },
      "spritePath": "playerTest.png",
      "hitPoints": 2
    },
    {
      "collisionBox": {
        "localVertices": [
          0.0,
          0.0,
          0.0,
          40.0,
          50.0,
          20.0
        ],
        "x": 2800.0,
        "y": 640.24084,
        "originX": 0.0,
        "originY": 0.0,
        "rotation": 0.0,
        "scaleX": 1.0,
        "scaleY": 1.0,
        "dirty": true
      },
      "pos": {
        "x": 2800.0,
        "y": 640.24084
      },
      "spritePath": "playerTest.png",
      "hitPoints": 2
    },
    {
      "collisionBox": {
        "localVertices": [
          0.0,
          0.0,
          0.0,
          40.0,
          50.0,
          20.0
        ],
        "x": 2900.0,
        "y": 530.7878,
        "originX": 0.0,
        "originY": 0.0,
        "rotation": 0.0,
        "scaleX": 1.0,
        "scaleY": 1.0,
        "dirty": true
      },
      "pos": {
        "x": 2900.0,
        "y": 530.7878
      },
      "spritePath": "playerTest.png",
      "hitPoints": 2
    },
    {
      "collisionBox": {
        "localVertices": [
          0.0,
          0.0,
          0.0,
          40.0,
          50.0,
          20.0
        ],
        "x": 3000.0,
        "y": 897.169,
        "originX": 0.0,
        "originY": 0.0,
        "rotation": 0.0,
        "scaleX": 1.0,
        "scaleY": 1.0,
        "dirty": true
      },
      "pos": {
        "x": 3000.0,
        "y": 897.169
      },
      "spritePath": "playerTest.png",
      "hitPoints": 2
    },
    {
      "collisionBox": {
        "localVertices": [
          0.0,
          0.0,
          0.0,
          40.0,
          50.0,
          20.0
        ],
        "x": 3100.0,
        "y": 456.7577,
        "originX": 0.0,
        "originY": 0.0,
        "rotation": 0.0,
        "scaleX": 1.0,
        "scaleY": 1.0,
        "dirty": true
      },
      "pos": {
        "x": 3100.0,
        "y": 456.7577
      },
      "spritePath": "playerTest.png",
      "hitPoints": 2
    },
    {
      "collisionBox": {
        "localVertices": [
          0.0,
          0.0,
          0.0,
          40.0,
          50.0,
          20.0
        ],
        "x": 3200.0,
        "y": 425.13596,
        "originX": 0.0,
        "originY": 0.0,
        "rotation": 0.0,
        "scaleX": 1.0,
        "scaleY": 1.0,
        "dirty": true
      },
      "pos": {
        "x": 3200.0,
        "y": 425.13596
      },
      "spritePath": "playerTest.png",
      "hitPoints": 2
    },
    {
      "collisionBox": {
        "localVertices": [
          0.0,
          0.0,
          0.0,
          40.0,
          50.0,
          20.0
        ],
        "x": 3300.0,
        "y": 459.58157,
        "originX": 0.0,
        "originY": 0.0,
        "rotation": 0.0,
        "scaleX": 1.0,
        "scaleY": 1.0,
        "dirty": true
      },
      "pos": {
        "x": 3300.0,
        "y": 459.58157
      },
      "spritePath": "playerTest.png",
      "hitPoints": 2
    },
    {
      "collisionBox": {
        "localVertices": [
          0.0,
          0.0,
          0.0,
          40.0,
          50.0,
          20.0
        ],
        "x": 3400.0,
        "y": 439.5332,
        "originX": 0.0,
        "originY": 0.0,
        "rotation": 0.0,
        "scaleX": 1.0,
        "scaleY": 1.0,
        "dirty": true
      },
      "pos": {
        "x": 3400.0,
        "y": 439.5332
      },
      "spritePath": "playerTest.png",
      "hitPoints": 2
    }
  ],
  "endState": false,
  "failState": false
}